aria2c/__init__.py
aria2c/__main__.py
aria2c/py.typed
aria2c/bin/aria2c
aria2-0.0.1b0.dist-info/METADATA
aria2-0.0.1b0.dist-info/WHEEL
aria2-0.0.1b0.dist-info/entry_points.txt
aria2-0.0.1b0.dist-info/licenses/LICENSE
aria2-0.0.1b0.dist-info/RECORD
