Metadata-Version: 2.1
Name: aria2
Version: 0.0.1b0
Summary: python wheel for aria2 static build.
Project-URL: Documentation, https://WSH032.github.io/aria2-wheel/
Project-URL: Source code, https://github.com/WSH032/aria2-wheel/
Author-email: Sean Wang <126865849+WSH032@users.noreply.github.com>
License: GNU GENERAL PUBLIC LICENSE
License-File: LICENSE
Keywords: aria2,aria2-static,aria2c,aria2c.exe
Classifier: Programming Language :: Python :: 3 :: Only
Classifier: Programming Language :: Python :: 3.8
Classifier: Programming Language :: Python :: 3.9
Classifier: Programming Language :: Python :: 3.10
Classifier: Programming Language :: Python :: 3.11
Classifier: Programming Language :: Python :: 3.12
Requires-Python: >=3.8
